ft_package_mbouayou/__init__.py
ft_package_mbouayou/ft_package.py
ft_package_mbouayou-0.0.1.dist-info/licenses/LICENSE
ft_package_mbouayou-0.0.1.dist-info/METADATA
ft_package_mbouayou-0.0.1.dist-info/WHEEL
ft_package_mbouayou-0.0.1.dist-info/top_level.txt
ft_package_mbouayou-0.0.1.dist-info/RECORD
