Metadata-Version: 2.4
Name: ft_package_mbouayou
Version: 0.0.1
Summary: 42 package
Author-email: Ye kanye <here@we-go.again>
License-Expression: MIT
Classifier: Programming Language :: Python :: 3
Classifier: Operating System :: OS Independent
Requires-Python: >=3.9
License-File: LICENSE
Dynamic: license-file
